tello_control/__init__.py
tello_control/controller.py
tello_control/experiment.py
tello_control/structs.py
tello_control/tello.py
tello_control/udp_interface.py
tello_control/utils.py
tello_control-1.0.1.dist-info/LICENSE
tello_control-1.0.1.dist-info/METADATA
tello_control-1.0.1.dist-info/WHEEL
tello_control-1.0.1.dist-info/top_level.txt
tello_control-1.0.1.dist-info/RECORD
