Metadata-Version: 2.1
Name: tello-control
Version: 1.0.1
Summary: A package for doing feedback control for the DJI Ryze Tello Drone
Author-email: Anmol Parande <parande.anmol@gmail.com>
License: GNU GENERAL PUBLIC LICENSE
Project-URL: Documentation, https://tello-control.readthedocs.io/en/latest/
Classifier: Programming Language :: Python :: 3
Requires-Python: >=3.7
License-File: LICENSE
